hai_assessments_sdk/__about__.py
hai_assessments_sdk/__init__.py
hai_assessments_sdk/assessment.py
hai_assessments_sdk/config.py
hai_assessments_sdk-0.0.11.dist-info/METADATA
hai_assessments_sdk-0.0.11.dist-info/WHEEL
hai_assessments_sdk-0.0.11.dist-info/licenses/LICENSE.txt
hai_assessments_sdk-0.0.11.dist-info/RECORD
